cjm_transcription_utils/__init__.py
cjm_transcription_utils/_modidx.py
cjm_transcription_utils/chunking.py
cjm_transcription_utils/core.py
cjm_transcription_utils/formatting.py
cjm_transcription_utils/librosa.py
cjm_transcription_utils/numerizer.py
cjm_transcription_utils/postprocessing.py
cjm_transcription_utils/pydub.py
cjm_transcription_utils/silero_vad.py
cjm_transcription_utils/timestamp_alignment.py
cjm_transcription_utils-0.0.3.dist-info/licenses/LICENSE
cjm_transcription_utils-0.0.3.dist-info/METADATA
cjm_transcription_utils-0.0.3.dist-info/WHEEL
cjm_transcription_utils-0.0.3.dist-info/entry_points.txt
cjm_transcription_utils-0.0.3.dist-info/top_level.txt
cjm_transcription_utils-0.0.3.dist-info/RECORD
