Metadata-Version: 2.4
Name: cjm-transcription-utils
Version: 0.0.3
Summary: Miscellaneous utilities for helping with audio transcription.
Home-page: https://github.com/cj-mills/cjm-transcription-utils
Author: Christian J. Mills
Author-email: 9126128+cj-mills@users.noreply.github.com
License: Apache Software License 2.0
Keywords: nbdev jupyter notebook python
Classifier: Development Status :: 4 - Beta
Classifier: Intended Audience :: Developers
Classifier: Natural Language :: English
Classifier: Programming Language :: Python :: 3.11
Classifier: Programming Language :: Python :: 3.12
Classifier: License :: OSI Approved :: Apache Software License
Requires-Python: >=3.11
License-File: LICENSE
Requires-Dist: silero-vad
Requires-Dist: num2words
Requires-Dist: librosa
Requires-Dist: pydub
Requires-Dist: RapidFuzz
Requires-Dist: numerizer
Provides-Extra: dev
Dynamic: author
Dynamic: author-email
Dynamic: classifier
Dynamic: description
Dynamic: description-content-type
Dynamic: home-page
Dynamic: keywords
Dynamic: license
Dynamic: license-file
Dynamic: provides-extra
Dynamic: requires-dist
Dynamic: requires-python
Dynamic: summary
